{
    "Diffusion": 0.08799999952316284,
    "Iterations": 3,
    "Size": 128,
    "Spawners": [
        {
            "Position": [
                63,
                63,
                63
            ],
            "Texture": 5,
            "Value": 3.0
        },
        {
            "Position": [
                63,
                1,
                63
            ],
            "Texture": 1,
            "Value": 2.0
        },
        {
            "Position": [
                1,
                63,
                63
            ],
            "Texture": 0,
            "Value": 2.0
        },
        {
            "Position": [
                63,
                63,
                1
            ],
            "Texture": 2,
            "Value": 2.0
        }
    ],
    "Viscosity": 0.16500000655651093
}